ach_calc/__init__.py
ach_calc-0.0.1.dist-info/LICENSE.txt
ach_calc-0.0.1.dist-info/METADATA
ach_calc-0.0.1.dist-info/WHEEL
ach_calc-0.0.1.dist-info/top_level.txt
ach_calc-0.0.1.dist-info/RECORD
